jaraco/ui/__init__.py
jaraco/ui/cmdline.py
jaraco/ui/editor.py
jaraco/ui/input.py
jaraco/ui/main.py
jaraco/ui/menu.py
jaraco/ui/progress.py
jaraco.ui-2.4.0.dist-info/LICENSE
jaraco.ui-2.4.0.dist-info/METADATA
jaraco.ui-2.4.0.dist-info/WHEEL
jaraco.ui-2.4.0.dist-info/top_level.txt
jaraco.ui-2.4.0.dist-info/RECORD
